unrealmate/__init__.py
unrealmate/cli.py
unrealmate/core/__init__.py
unrealmate/core/config.py
unrealmate/core/logger.py
unrealmate/core/signature.py
unrealmate/core/assets/__init__.py
unrealmate/core/assets/duplicates.py
unrealmate/core/assets/organizer.py
unrealmate/core/assets/scanner.py
unrealmate/core/blueprint/__init__.py
unrealmate/core/blueprint/parser.py
unrealmate/core/blueprint/report.py
unrealmate/core/build/__init__.py
unrealmate/core/build/ci_generator.py
unrealmate/core/git/__init__.py
unrealmate/core/git/cleanup.py
unrealmate/core/git/lfs.py
unrealmate/core/performance/__init__.py
unrealmate/core/performance/memory_auditor.py
unrealmate/core/performance/profiler.py
unrealmate/core/performance/shader_analyzer.py
unrealmate/core/plugins/__init__.py
unrealmate/core/plugins/manager.py
unrealmate/templates/gitattributes.template
unrealmate/templates/gitignore.template
unrealmate-1.0.10.dist-info/licenses/LICENSE
unrealmate-1.0.10.dist-info/METADATA
unrealmate-1.0.10.dist-info/WHEEL
unrealmate-1.0.10.dist-info/entry_points.txt
unrealmate-1.0.10.dist-info/top_level.txt
unrealmate-1.0.10.dist-info/RECORD
