Metadata-Version: 2.4
Name: unrealmate
Version: 1.0.10
Summary: Professional CLI toolkit for Unreal Engine developers - Complete with performance profiling, plugin management, CI/CD generation, and personal branding by gktrk363
Home-page: https://github.com/gktrk363/unrealmate
Author: gktrk363
License: MIT
Project-URL: Homepage, https://github.com/gktrk363/unrealmate
Project-URL: Repository, https://github.com/gktrk363/unrealmate
Keywords: unreal,unreal-engine,gamedev,cli,toolkit,performance,profiler,plugins,cicd
Classifier: Development Status :: 5 - Production/Stable
Classifier: Intended Audience :: Developers
Classifier: License :: OSI Approved :: MIT License
Classifier: Programming Language :: Python :: 3.10
Classifier: Programming Language :: Python :: 3.11
Classifier: Programming Language :: Python :: 3.12
Requires-Python: >=3.10
License-File: LICENSE
Requires-Dist: typer>=0.9.0
Requires-Dist: rich>=13.0.0
Requires-Dist: toml>=0.10.2
Dynamic: home-page
Dynamic: license-file
Dynamic: requires-python
